quax_blocks/__init__.py
quax_blocks/_version.py
quax_blocks/_version.pyi
quax_blocks/py.typed
quax_blocks/_src/__init__.py
quax_blocks/_src/binary.py
quax_blocks/_src/container.py
quax_blocks/_src/copy.py
quax_blocks/_src/example.py
quax_blocks/_src/rich.py
quax_blocks/_src/round.py
quax_blocks/_src/unary.py
quax_blocks-0.4.0.dist-info/METADATA
quax_blocks-0.4.0.dist-info/WHEEL
quax_blocks-0.4.0.dist-info/licenses/LICENSE
quax_blocks-0.4.0.dist-info/RECORD
