Metadata-Version: 2.4
Name: quax_blocks
Version: 0.4.0
Summary: Building blocks for Quax classes
Project-URL: Homepage, https://github.com/GalacticDynamics/quax-blocks
Project-URL: Bug Tracker, https://github.com/GalacticDynamics/quax-blocks/issues
Project-URL: Discussions, https://github.com/GalacticDynamics/quax-blocks/discussions
Project-URL: Changelog, https://github.com/GalacticDynamics/quax-blocks/releases
Author-email: Nathaniel Starkman <nstarman@users.noreply.github.com>
License-File: LICENSE
Classifier: Development Status :: 1 - Planning
Classifier: Intended Audience :: Developers
Classifier: Intended Audience :: Science/Research
Classifier: License :: OSI Approved :: BSD License
Classifier: Operating System :: OS Independent
Classifier: Programming Language :: Python
Classifier: Programming Language :: Python :: 3
Classifier: Programming Language :: Python :: 3 :: Only
Classifier: Programming Language :: Python :: 3.11
Classifier: Programming Language :: Python :: 3.12
Classifier: Programming Language :: Python :: 3.13
Classifier: Topic :: Scientific/Engineering
Classifier: Typing :: Typed
Requires-Python: >=3.11
Requires-Dist: jax>=0.5.3
Requires-Dist: jaxlib>=0.5.3
Requires-Dist: jaxtyping>=0.3.3
Requires-Dist: optype<0.14,>=0.13; python_version < '3.12'
Requires-Dist: optype>=0.14.0; python_version >= '3.12'
Requires-Dist: plum-dispatch>=2.5.7
Requires-Dist: quax>=0.2.1
Requires-Dist: quaxed>=0.10.2
